setup.py
gaussian/Binomialdistribution.py
gaussian/Gaussiandistribution.py
gaussian/Generaldistribution.py
gaussian/__init__.py
gaussian.egg-info/PKG-INFO
gaussian.egg-info/SOURCES.txt
gaussian.egg-info/dependency_links.txt
gaussian.egg-info/not-zip-safe
gaussian.egg-info/top_level.txt